momentfm/__init__.py
momentfm/common.py
momentfm/data/__init__.py
momentfm/data/anomaly_detection_dataset.py
momentfm/data/base.py
momentfm/data/classification_dataset.py
momentfm/data/informer_dataset.py
momentfm/data/ptbxl_classification_dataset.py
momentfm/data/synthetic_data.py
momentfm/models/__init__.py
momentfm/models/moment.py
momentfm/models/statistical_classifiers.py
momentfm/models/layers/__init__.py
momentfm/models/layers/embed.py
momentfm/models/layers/revin.py
momentfm/utils/__init__.py
momentfm/utils/anomaly_detection_metrics.py
momentfm/utils/data.py
momentfm/utils/forecasting_metrics.py
momentfm/utils/masking.py
momentfm/utils/utils.py
momentfm-0.1.4.dist-info/METADATA
momentfm-0.1.4.dist-info/WHEEL
momentfm-0.1.4.dist-info/licenses/LICENSE
momentfm-0.1.4.dist-info/RECORD
