Metadata-Version: 2.4
Name: momentfm
Version: 0.1.4
Summary: MOMENT: A Family of Open Time Series Foundation Models
Project-URL: Homepage, https://moment-timeseries-foundation-model.github.io/
Project-URL: Repository, https://github.com/moment-timeseries-foundation-model/moment
Project-URL: Bug Tracker, https://github.com/moment-timeseries-foundation-model/moment/issues
Author: Konrad Szafer, Arjun Choudhry, Yifu Cai, Shuo Li, Artur Dubrawski
Author-email: Mononito Goswami <mononitog@hotmail.com>
Maintainer-email: Mononito Goswami <mononitog@hotmail.com>, Konrad Szafer <szafer.konrad@gmail.com>, Yifu Cai <yifuc@andrew.cmu.edu>, Michal Wilinski <mwilisk@andrew.cmu.edu>
License: MIT License
License-File: LICENSE
Keywords: anomaly detection,classification,forecasting,foundation models,huggingface,imputation,large language models,moment,pytorch,time series,transformers
Classifier: Programming Language :: Python
Requires-Python: >=3.10
Requires-Dist: huggingface-hub==0.24.0
Requires-Dist: numpy==1.25.2
Requires-Dist: torch~=2.0
Requires-Dist: transformers==4.33.3
